pytest_tornado/__init__.py
pytest_tornado/plugin.py
pytest_tornado-0.8.1.dist-info/LICENSE
pytest_tornado-0.8.1.dist-info/METADATA
pytest_tornado-0.8.1.dist-info/WHEEL
pytest_tornado-0.8.1.dist-info/entry_points.txt
pytest_tornado-0.8.1.dist-info/top_level.txt
pytest_tornado-0.8.1.dist-info/RECORD
